zprofile-1.0.13.dist-info/METADATA
zprofile-1.0.13.dist-info/LICENSE
zprofile-1.0.13.dist-info/top_level.txt
zprofile-1.0.13.dist-info/WHEEL
zprofile-1.0.13.dist-info/RECORD
zprofile/__init__.py
zprofile/profile_pb2.py
zprofile/__version__.py
zprofile/builder.py
zprofile/cpu_profiler.py
zprofile/wall_profiler.py
zprofile/_profiler.cpython-312-x86_64-linux-gnu.so
