Metadata-Version: 2.1
Name: zprofile
Version: 1.0.13
Summary: Statistical CPU and wall-clock profilers for Python
Home-page: https://github.com/timpalpant/zprofile
Author: Timothy Palpant
License: Apache License, Version 2.0
Keywords: cloud profiler
Classifier: Development Status :: 5 - Production/Stable
Classifier: Intended Audience :: Developers
Classifier: License :: OSI Approved :: Apache Software License
Classifier: Programming Language :: Python :: 3.7
Classifier: Programming Language :: Python :: 3.8
Classifier: Programming Language :: Python :: 3.9
Classifier: Programming Language :: Python :: 3.10
Classifier: Programming Language :: Python :: 3.11
License-File: LICENSE
Requires-Dist: protobuf
